.gitattributes
ChangeLog.md
LICENSE
MANIFEST.in
README.md
pyproject.toml
setup.cfg
.github/workflows/ci.yml
.github/workflows/release.yml
ci/conda_host_env.yml
ci/conda_requirements.txt
ci/requirements.lint.txt
micov/__init__.py
micov/_constants.py
micov/_convert.py
micov/_cov.py
micov/_io.py
micov/_per_sample.py
micov/_plot.py
micov/_quant.py
micov/_rank.py
micov/_utils.py
micov/_view.py
micov/cli.py
micov.egg-info/PKG-INFO
micov.egg-info/SOURCES.txt
micov.egg-info/dependency_links.txt
micov.egg-info/entry_points.txt
micov.egg-info/requires.txt
micov.egg-info/top_level.txt
micov/tests/__init__.py
micov/tests/test_convert.py
micov/tests/test_cov.py
micov/tests/test_io.py
micov/tests/test_per_sample.py
micov/tests/test_quant.py
micov/tests/test_view.py
micov/tests/test_data/__init__.py
micov/tests/test_data/test.sam.xz