Metadata-Version: 2.1
Name: micov
Version: 2025.3
Author-email: Daniel McDonald <damcdonald@ucsd.edu>, Sherlyn Weng <y1weng@ucsd.edu>, Caitlin Guccione <cguccion@ucsd.edu>
License: ==========================
Keywords: microbiome,bioinformatics
Classifier: Environment :: Console
Classifier: Intended Audience :: Science/Research
Classifier: License :: OSI Approved :: BSD License
Classifier: Operating System :: OS Independent
Classifier: Programming Language :: Python :: Implementation :: CPython
Classifier: Programming Language :: Python :: 3.9
Classifier: Programming Language :: Python :: 3.10
Classifier: Programming Language :: Python :: 3.11
Classifier: Programming Language :: Python :: 3.12
Classifier: Programming Language :: Python :: 3.13
Classifier: Topic :: Scientific/Engineering
Requires-Python: >=3.9
License-File: LICENSE
Requires-Dist: click
Requires-Dist: scipy
Requires-Dist: pyarrow<16.0.0
Requires-Dist: polars-u64-idx<1.23.0
Requires-Dist: numba
Requires-Dist: matplotlib>=3.9.0
Requires-Dist: duckdb>=1.2.0
Requires-Dist: pytest
